{
  "parent": "mcremake:recipes/combat/turtle_helmet",
  "criteria": {
    "crafted_leather_chestplate": {
      "trigger": "minecraft:recipe_crafted",
      "conditions": {
        "recipe_id": "minecraft:leather_chestplate"
      }
    }
  },
  "sends_telemetry_event": false,
  "display": {
	"announce_to_chat": false,
	"show_toast": false,
    "description": {
      "translate": ""
    },
    "icon": {
      "count": 1,
      "id": "minecraft:leather_chestplate"
    },
    "title": {
      "translate": "item.minecraft.leather_chestplate"
    }
  },
  "requirements": [
    [
      "crafted_leather_chestplate"
    ]
  ]
}